warrior/README.txt
warrior/Warrior
warrior/Warriormigrate
warrior/__init__.py
warrior/warrior_upgrade
warrior/Actions/__init__.py
warrior/Actions/CommonActions/__init__.py
warrior/Actions/CommonActions/common_actions.py
warrior/Actions/LogActions/__init__.py
warrior/Actions/LogActions/log_actions.py
warrior/Framework/__init__.py
warrior/Framework/ClassUtils/__init__.py
warrior/Framework/ClassUtils/configuration_element_class.py
warrior/Framework/ClassUtils/database_utils_class.py
warrior/Framework/ClassUtils/json_utils_class.py
warrior/Framework/ClassUtils/kafka_utils_class.py
warrior/Framework/ClassUtils/testdata_class.py
warrior/Framework/Gnmi/gnmi_cli
warrior/Framework/OSS/__init__.py
warrior/Framework/OSS/bottle.py
warrior/Framework/OSS/xmltodict.py
warrior/Framework/Utils/__init__.py
warrior/Framework/Utils/config_Utils.py
warrior/Framework/Utils/data_Utils.py
warrior/Framework/Utils/datetime_utils.py
warrior/Framework/Utils/dict_Utils.py
warrior/Framework/Utils/email_utils.py
warrior/Framework/Utils/encryption_utils.py
warrior/Framework/Utils/file_Utils.py
warrior/Framework/Utils/import_utils.py
warrior/Framework/Utils/print_Utils.py
warrior/Framework/Utils/string_Utils.py
warrior/Framework/Utils/testcase_Utils.py
warrior/Framework/Utils/testrandom_utils.py
warrior/Framework/Utils/xml_Utils.py
warrior/ProductDrivers/__init__.py
warrior/ProductDrivers/common_driver.py
warrior/ProductDrivers/log_driver.py
warrior/Tools/__init__.py
warrior/Tools/generic_samples.db
warrior/Tools/w_settings.xml
warrior/Tools/admin/secret.key
warrior/Tools/connection/connect_settings.xml
warrior/Tools/connection/configs/1finity_command_data.xml
warrior/Tools/connection/configs/ubuntu_command_data.xml
warrior/Tools/database/database_config.xml
warrior/Tools/jira/jira_config.xml
warrior/Tools/reporting/html_results_template.html
warrior/Tools/reporting/wjunit_to_xunit.xsl
warrior/Tools/xsd/warrior_project.xsd
warrior/Tools/xsd/warrior_suite.xsd
warrior/Tools/xsd/warrior_testcase.xsd
warriorframework-4.6.0.dist-info/AUTHORS
warriorframework-4.6.0.dist-info/LICENSE
warriorframework-4.6.0.dist-info/METADATA
warriorframework-4.6.0.dist-info/WHEEL
warriorframework-4.6.0.dist-info/top_level.txt
warriorframework-4.6.0.dist-info/RECORD
