Metadata-Version: 2.1
Name: warriorframework
Version: 4.6.0
Summary: Warrior Framework is an open source Automation Framework
Home-page: https://github.com/warriorframework/warriorframework_py3
Author: warriorteam
Author-email: frameworkwarrior@gmail.com
License: UNKNOWN
Project-URL: Documentation, http://warriorframework.org/
Project-URL: Source Code, https://github.com/warriorframework/warriorframework_py3
Platform: UNKNOWN
Classifier: Development Status :: 5 - Production/Stable
Classifier: License :: OSI Approved :: Apache Software License
Classifier: Programming Language :: Python :: 3.6
Requires-Dist: kafka-python (==1.4.6)
Requires-Dist: configobj (==5.0.6)
Requires-Dist: requests (==2.21.0)
